iverilog/dff.v

//dff modules represents a D type flip-flop
module dff(d,clk,q,qn);
	input d,clk;
	output q,qn;
	reg q,qn;

	//Initialize flip-flop outputs
	initial begin q=0; qn=1; end

	//Change output on positive clock edge
	always @(posedge clk) 
	begin
		q <= d;
		qn <= !d;
	end
endmodule

//Tester module sends a periodic clock signal to the flip-flop
module tester(q,qn,clk,d);
	input q,qn;
	output clk,d;
	reg clk,d;

	//Run the test once
	initial
	begin
		clk=0;
		//Dump results of the simulation to ff.cvd
		$dumpfile("dff.vcd");
		$dumpvars;
		//Generate input signal d
		   d=0; #9 d=1; #1 d=0; #1 d=1; #2 d=0; #1 d=1; #12 d=0;
		#1 d=1; #2 d=0; #1 d=1; #1 d=0; #1 d=1; #1 d=0; # 7 d=1;
		#8 $finish;
	end

	//Generate periodic clock signal
	always
	begin
		#4 clk=!clk;
	end
endmodule

//Test bench connects the flip-flop to the tester module
module testbench;
	wire clk,d,q,qn;
	dff ff1(d,clk,q,qn);
	tester tst1(q,qn,clk,d);
endmodule

iverilog/dff.vcd
$date
	Sun Dec 09 15:13:22 2018
$end
$version
	Icarus Verilog
$end
$timescale
	1s
$end
$scope module testbench $end
$var wire 1 ! qn $end
$var wire 1 " q $end
$var wire 1 # d $end
$var wire 1 $ clk $end
$scope module ff1 $end
$var wire 1 # d $end
$var wire 1 $ clk $end
$var reg 1 " q $end
$var reg 1 ! qn $end
$upscope $end
$scope module tst1 $end
$var wire 1 " q $end
$var wire 1 ! qn $end
$var reg 1 $ clk $end
$var reg 1 # d $end
$upscope $end
$upscope $end
$enddefinitions $end
#0
$dumpvars
0$
0#
0"
1!
$end
#4
1$
#8
0$
#9
1#
#10
0#
#11
1#
#12
0!
1"
1$
#13
0#
#14
1#
#16
0$
#20
1$
#24
0$
#26
0#
#27
1#
#28
1$
#29
0#
#30
1#
#31
0#
#32
1#
0$
#33
0#
#36
1!
0"
1$
#40
0$
1#
#44
0!
1"
1$
