iverilog/example_3_1.v
// Verilog model of circuit of Figure 3.35 in Digital Systems 5th ed. 

module example_3_1(A, B, C, D, E);
   
   output D, E;
   input  A, B, C;
   wire   w1;

   and G1(w1, A, B);	//w1<- A & B
   not G2(E, C);		//E<- not C
   or  G3(D, w1, E);	//D<- E || w1

endmodule

iverilog/example_3_1_tb.v
// Verilog test bench for example_3_1
`timescale 1ns/100ps
`include "example_3_1.v"

module example_3_1_tb;

   wire A, B, C, D, E;
   integer k=0;

   assign {A,B,C} = k;
   example_3_1 the_circuit(A, B, C, D, E);

   initial begin

      $dumpfile("example_3_1.vcd");
      $dumpvars(0, example_3_1_tb);

      for (k=0; k<8; k=k+1)
        #5 $display("done testing case %d", k);

      $finish;

   end

endmodule

iverilog/example_3_1.vcd
$date
	Thu Nov 08 05:18:59 2018
$end
$version
	Icarus Verilog
$end
$timescale
	100ps
$end
$scope module example_3_1_tb $end
$var wire 1 ! E $end
$var wire 1 " D $end
$var wire 1 # C $end
$var wire 1 $ B $end
$var wire 1 % A $end
$var integer 32 & k [31:0] $end
$scope module the_circuit $end
$var wire 1 % A $end
$var wire 1 $ B $end
$var wire 1 # C $end
$var wire 1 " D $end
$var wire 1 ! E $end
$var wire 1 ' w1 $end
$upscope $end
$upscope $end
$enddefinitions $end
#0
$dumpvars
0'
b0 &
0%
0$
0#
1"
1!
$end
#50
0"
0!
1#
b1 &
#100
1"
1!
0#
1$
b10 &
#150
0"
0!
1#
b11 &
#200
1"
1!
0#
0$
1%
b100 &
#250
0"
0!
1#
b101 &
#300
1"
1!
1'
0#
1$
b110 &
#350
0!
1#
b111 &
#400
1!
0'
0#
0$
0%
b1000 &
